freetextresponse/__init__.py
freetextresponse/models.py
freetextresponse/settings.py
freetextresponse/views.py
freetextresponse/xblocks.py
freetextresponse/mixins/__init__.py
freetextresponse/mixins/dates.py
freetextresponse/mixins/fragment.py
freetextresponse/mixins/i18n.py
freetextresponse/mixins/scenario.py
freetextresponse/mixins/user.py
freetextresponse/public/view.css
freetextresponse/public/view.js
freetextresponse/public/images/correct-icon.png
freetextresponse/public/images/incorrect-icon.png
freetextresponse/public/images/unanswered-icon.png
freetextresponse/scenarios/free-text-response-many.xml
freetextresponse/scenarios/free-text-response-single.xml
freetextresponse/templates/view.html
freetextresponse/translations/config.yaml
xblock_free_text_response-4.1.0.dist-info/LICENSE
xblock_free_text_response-4.1.0.dist-info/METADATA
xblock_free_text_response-4.1.0.dist-info/WHEEL
xblock_free_text_response-4.1.0.dist-info/entry_points.txt
xblock_free_text_response-4.1.0.dist-info/top_level.txt
xblock_free_text_response-4.1.0.dist-info/RECORD
